{
  "name": "oly",
  "modules": [
    {
      "name": "oly-core",
      "icon": "sim-card",
      "decorators": [
        "kernel/decorators/inject",
        "kernel/decorators/state",
        "kernel/decorators/env",
        "kernel/decorators/on"
      ],
      "services": [
        "kernel/Kernel.ts",
        "logger/Logger.ts"
      ]
    },
    {
      "name": "oly-json",
      "icon": "ninja",
      "decorators": [
        "decorators/field",
        "decorators/array"
      ],
      "services": [
        "services/JsonService.ts"
      ]
    },
    {
      "name": "oly-react",
      "icon": "delta",
      "decorators": [
        "core/decorators/attach"
      ],
      "services": [
        "router/services/Browser.ts"
      ]
    },
    {
      "name": "oly-api",
      "icon": "satellite",
      "decorators": [
        "core/decorators/get",
        "core/decorators/body"
      ],
      "services": [
        "core/providers/ApiProvider.ts"
      ]
    }
  ]
}
